MANIFEST.in
README.txt
setup.py
docs/HISTORY.txt
emencia/__init__.py
emencia.django.links.egg-info/PKG-INFO
emencia.django.links.egg-info/SOURCES.txt
emencia.django.links.egg-info/dependency_links.txt
emencia.django.links.egg-info/entry_points.txt
emencia.django.links.egg-info/namespace_packages.txt
emencia.django.links.egg-info/not-zip-safe
emencia.django.links.egg-info/requires.txt
emencia.django.links.egg-info/top_level.txt
emencia/django/__init__.py
emencia/django/links/__init__.py
emencia/django/links/admin.py
emencia/django/links/models.py
emencia/django/links/tests.py
emencia/django/links/testsettings.py
emencia/django/links/urls.py
emencia/django/links/views.py
emencia/django/links/templatetags/__init__.py
emencia/django/links/templatetags/links_monitoring.py