Metadata-Version: 1.0
Name: emencia.django.links
Version: 0.2
Summary: Django app that create a links directory
Home-page: UNKNOWN
Author: Lafaye Philippe
Author-email: lafaye@emencia.com
License: AGPL
Keywords: django links
Platform: UNKNOWN
Classifier: Development Status :: 4 - Beta
Classifier: Framework :: Django
Classifier: Intended Audience :: Developers
Classifier: License :: OSI Approved :: GNU Affero General Public License v3
Classifier: Operating System :: OS Independent
Classifier: Programming Language :: Python
Classifier: Topic :: Internet :: WWW/HTTP
